examples/__init__.py
examples/print_help_manual.py
examples/interesting_examples/__init__.py
examples/interesting_examples/active_learning_example.py
examples/interesting_examples/adult_example.py
examples/interesting_examples/anomalies_in_dataset_example.py
examples/interesting_examples/california_housing_example.py
examples/interesting_examples/kddcup99_example.py
examples/interesting_examples/prediction_uncertainty_adult_example.py
examples/interesting_examples/prediction_uncertainty_california_example.py
examples/interesting_examples/simple_example_classification.py
examples/interesting_examples/simple_example_regression.py
examples/interesting_examples/titanic_example.py
examples/toy_examples/__init__.py
examples/toy_examples/example_prediction_explanation.py
examples/toy_examples/example_prediction_uncertainty.py
examples/toy_examples/example_quality_report.py
examples/toy_examples/example_scoring_report.py
examples/toy_examples/example_sensitivity_analysis.py
pytolemaic/__init__.py
pytolemaic/pytrust.py
pytolemaic/pytrust_report.py
pytolemaic/version.py
pytolemaic/analysis_logic/__init__.py
pytolemaic/analysis_logic/quality_report.py
pytolemaic/analysis_logic/dataset_analysis/__init__.py
pytolemaic/analysis_logic/dataset_analysis/anomaly_values_in_data.py
pytolemaic/analysis_logic/dataset_analysis/anomaly_values_in_data_report.py
pytolemaic/analysis_logic/dataset_analysis/covariance_shift_report.py
pytolemaic/analysis_logic/dataset_analysis/covriance_shift.py
pytolemaic/analysis_logic/dataset_analysis/dataset_analysis.py
pytolemaic/analysis_logic/dataset_analysis/dataset_analysis_report.py
pytolemaic/analysis_logic/model_analysis/__init__.py
pytolemaic/analysis_logic/model_analysis/scoring/__init__.py
pytolemaic/analysis_logic/model_analysis/scoring/scoring.py
pytolemaic/analysis_logic/model_analysis/scoring/scoring_report.py
pytolemaic/analysis_logic/model_analysis/sensitivity/__init__.py
pytolemaic/analysis_logic/model_analysis/sensitivity/sensitivity.py
pytolemaic-0.15.4.dist-info/METADATA
pytolemaic-0.15.4.dist-info/WHEEL
pytolemaic-0.15.4.dist-info/top_level.txt
pytolemaic-0.15.4.dist-info/RECORD
