Metadata-Version: 2.1
Name: pytolemaic
Version: 0.15.4
Summary: Package for ML model analysis
Home-page: https://github.com/broundal/Pytolemaic
Author: Orion Talmi
Author-email: otalmi@gmail.com
License: UNKNOWN
Platform: Linux
Classifier: Programming Language :: Python :: 3
Classifier: License :: Free To Use But Restricted
Classifier: Operating System :: Unix
Classifier: Topic :: Scientific/Engineering :: Artificial Intelligence
Requires-Python: >=3.6.*
Requires-Dist: numpy (>=1.17.0)
Requires-Dist: pandas (>=0.24.2)
Requires-Dist: scipy (>=1.3.0)
Requires-Dist: scikit-learn (>=0.22.1)
Requires-Dist: lime (>=0.1.1.36)
Requires-Dist: matplotlib (>=3.0.3)
Requires-Dist: xgboost (>=1.4.2)
